src/redis_compatibility_test/redis_compatibility_test.py
redis_compatibility_test-0.0.5.dist-info/METADATA
redis_compatibility_test-0.0.5.dist-info/WHEEL
redis_compatibility_test-0.0.5.dist-info/entry_points.txt
redis_compatibility_test-0.0.5.dist-info/licenses/LICENSE
redis_compatibility_test-0.0.5.dist-info/RECORD
