Metadata-Version: 2.1
Name: redis-compatibility-test
Version: 0.0.5
Summary: A tool to detect which version of Redis your Redis-Like database is compatible with.
Project-URL: Homepage, https://github.com/tair-opensource/compatibility-test-suite-for-redis
Project-URL: Bug Tracker, https://github.com/tair-opensource/compatibility-test-suite-for-redis/issues
Author-email: daz-3ux <daz-3ux@proton.me>, yangbodong22011 <bodong.ybd@alibaba-inc.com>
License-File: LICENSE
Classifier: License :: OSI Approved :: MIT License
Classifier: Operating System :: OS Independent
Classifier: Programming Language :: Python :: 3
Requires-Python: >=3.7
Requires-Dist: dataclasses
Requires-Dist: pyyaml>=6.0
Requires-Dist: redis>=4.4.4
